dtc/__init__.py
dtc-0.1.1.dist-info/WHEEL
dtc-0.1.1.dist-info/METADATA
dtc-0.1.1.dist-info/RECORD
